[
  {
    "front": "What year did the United States declare independence?",
    "back": "1776",
    "learned": true
  },
  {
    "front": "What historical event began on July 14, 1789, with the storming of the Bastille?",
    "back": "The French Revolution",
    "learned": true
  },
  {
    "front": "Who wrote the Communist Manifesto?",
    "back": "Karl Marx and Friedrich Engels",
    "learned": true
  },
  {
    "front": "What empire was ruled by Genghis Khan?",
    "back": "The Mongol Empire",
    "learned": true
  },
  {
    "front": "What wall fell in 1989, symbolizing the end of the Cold War?",
    "back": "The Berlin Wall",
    "learned": true
  },
  {
    "front": "What was the name of the ship that brought the Pilgrims to America in 1620?",
    "back": "The Mayflower",
    "learned": true
  },
  {
    "front": "Which civilization built Machu Picchu?",
    "back": "The Inca civilization",
    "learned": true
  },
  {
    "front": "Who was the first President of the United States?",
    "back": "George Washington",
    "learned": true
  }
]